{
  "id": "",
  "name": "",
  "font_family": "iconfont",
  "css_prefix_text": "icon-",
  "description": "",
  "glyphs": [
    {
      "icon_id": "1310098",
      "name": "地址",
      "font_class": "dizhi",
      "unicode": "e624",
      "unicode_decimal": 58916
    },
    {
      "icon_id": "3462492",
      "name": "圈箭头向左",
      "font_class": "quanjiantouxiangzuo",
      "unicode": "e60c",
      "unicode_decimal": 58892
    },
    {
      "icon_id": "3569800",
      "name": "圈箭头向左",
      "font_class": "prev",
      "unicode": "e503",
      "unicode_decimal": 58627
    },
    {
      "icon_id": "5373211",
      "name": "下箭头",
      "font_class": "arrow-left",
      "unicode": "e54a",
      "unicode_decimal": 58698
    },
    {
      "icon_id": "5488308",
      "name": "qq ",
      "font_class": "qq",
      "unicode": "e61f",
      "unicode_decimal": 58911
    },
    {
      "icon_id": "5610935",
      "name": "塔吊",
      "font_class": "tadiao",
      "unicode": "e622",
      "unicode_decimal": 58914
    },
    {
      "icon_id": "6155088",
      "name": "qq",
      "font_class": "qq1",
      "unicode": "e632",
      "unicode_decimal": 58930
    },
    {
      "icon_id": "6546688",
      "name": "上箭头",
      "font_class": "up",
      "unicode": "e607",
      "unicode_decimal": 58887
    },
    {
      "icon_id": "7840757",
      "name": "用户",
      "font_class": "user",
      "unicode": "e616",
      "unicode_decimal": 58902
    },
    {
      "icon_id": "7909135",
      "name": "右箭头",
      "font_class": "youjiantou",
      "unicode": "e611",
      "unicode_decimal": 58897
    },
    {
      "icon_id": "8692716",
      "name": "公司新闻",
      "font_class": "gongsixinwen",
      "unicode": "e693",
      "unicode_decimal": 59027
    },
    {
      "icon_id": "8853249",
      "name": "微博",
      "font_class": "weibo",
      "unicode": "e601",
      "unicode_decimal": 58881
    },
    {
      "icon_id": "10025364",
      "name": "下箭头",
      "font_class": "b_jiantou02",
      "unicode": "e501",
      "unicode_decimal": 58625
    },
    {
      "icon_id": "10030603",
      "name": "邮箱",
      "font_class": "youxiang",
      "unicode": "e630",
      "unicode_decimal": 58928
    },
    {
      "icon_id": "10819112",
      "name": "待开会议",
      "font_class": "zaixianhuiyi",
      "unicode": "e625",
      "unicode_decimal": 58917
    },
    {
      "icon_id": "11646436",
      "name": "电  话",
      "font_class": "dianhua",
      "unicode": "e613",
      "unicode_decimal": 58899
    },
    {
      "icon_id": "13503931",
      "name": "咨询",
      "font_class": "zixun",
      "unicode": "e63b",
      "unicode_decimal": 58939
    },
    {
      "icon_id": "14552468",
      "name": "全屏",
      "font_class": "quanping",
      "unicode": "eac8",
      "unicode_decimal": 60104
    },
    {
      "icon_id": "17630104",
      "name": "加号",
      "font_class": "hao",
      "unicode": "e61b",
      "unicode_decimal": 58907
    },
    {
      "icon_id": "19195695",
      "name": "缩小",
      "font_class": "suoxiao",
      "unicode": "e623",
      "unicode_decimal": 58915
    },
    {
      "icon_id": "19518808",
      "name": "电 话",
      "font_class": "dianhua1",
      "unicode": "e608",
      "unicode_decimal": 58888
    },
    {
      "icon_id": "19753226",
      "name": "微信",
      "font_class": "weixin",
      "unicode": "e8c5",
      "unicode_decimal": 59589
    },
    {
      "icon_id": "19758673",
      "name": "微信",
      "font_class": "weixin1",
      "unicode": "e658",
      "unicode_decimal": 58968
    }
  ]
}
